pclp/__init__.py
pclp/_init_paths.py
pclp/cli.py
pclp/cpg/__init__.py
pclp/cpg/bgm.py
pclp/cpg/causal_model.py
pclp/cpg/resnet.py
pclp/cpg/sagan.py
pclp-0.1.0.dist-info/LICENSE
pclp-0.1.0.dist-info/METADATA
pclp-0.1.0.dist-info/WHEEL
pclp-0.1.0.dist-info/entry_points.txt
pclp-0.1.0.dist-info/top_level.txt
pclp-0.1.0.dist-info/RECORD
